kobo2pandas/__init__.py
kobo2pandas/app.py
kobo2pandas/client.py
kobo2pandas/processor.py
kobo2pandas/types.py
kobo2pandas/utils.py
kobo2pandas-0.9.0.dist-info/licenses/LICENSE
kobo2pandas-0.9.0.dist-info/METADATA
kobo2pandas-0.9.0.dist-info/WHEEL
kobo2pandas-0.9.0.dist-info/top_level.txt
kobo2pandas-0.9.0.dist-info/RECORD
