Metadata-Version: 2.4
Name: kobo2pandas
Version: 0.9.0
Summary: Desde la API de Kobo a pandas.DataFrame
Author-email: Diego Mora <morabdiego@gmail.com>
Maintainer-email: Diego Mora <morabdiego@gmail.com>
License: MIT
Project-URL: Homepage, https://github.com/morabdiego/kobo2pandas
Project-URL: Documentation, https://github.com/morabdiego/kobo2pandas#readme
Project-URL: Repository, https://github.com/morabdiego/kobo2pandas
Project-URL: Bug Tracker, https://github.com/morabdiego/kobo2pandas/issues
Keywords: kobo,kobotoolbox,data-extraction,pandas,excel,humanitarian,surveys,data-processing
Classifier: Development Status :: 5 - Production/Stable
Classifier: Intended Audience :: Developers
Classifier: Intended Audience :: Science/Research
Classifier: License :: OSI Approved :: MIT License
Classifier: Operating System :: OS Independent
Classifier: Programming Language :: Python :: 3
Classifier: Programming Language :: Python :: 3.8
Classifier: Programming Language :: Python :: 3.9
Classifier: Programming Language :: Python :: 3.10
Classifier: Programming Language :: Python :: 3.11
Classifier: Programming Language :: Python :: 3.12
Classifier: Topic :: Scientific/Engineering :: Information Analysis
Classifier: Topic :: Software Development :: Libraries :: Python Modules
Classifier: Topic :: Utilities
Requires-Python: >=3.8
License-File: LICENSE
Requires-Dist: pandas>=1.5.0
Requires-Dist: openpyxl>=3.0.0
Requires-Dist: python-dotenv>=0.19.0
Requires-Dist: requests>=2.28.0
Provides-Extra: dev
Requires-Dist: build>=0.8.0; extra == "dev"
Requires-Dist: twine>=4.0.0; extra == "dev"
Requires-Dist: pytest>=7.0.0; extra == "dev"
Requires-Dist: pytest-cov>=4.0.0; extra == "dev"
Requires-Dist: black>=22.0.0; extra == "dev"
Requires-Dist: flake8>=5.0.0; extra == "dev"
Requires-Dist: mypy>=1.0.0; extra == "dev"
Dynamic: license-file
